<?xml version="1.0" encoding="utf-8"?>
<config xmlns="urn:ietf:params:xml:ns:netconf:base:1.0">
  <interfaces 
  xmlns="urn:ietf:params:xml:ns:yang:ietf-interfaces"
  xmlns:ianaift="urn:ietf:params:xml:ns:yang:iana-if-type"
  xmlns:dot1q-types="urn:ieee:std:802.1Q:yang:ieee802-dot1q-types"
  xmlns:if-ext="urn:ietf:params:xml:ns:yang:ietf-if-extensions">
    <interface>
      <name>eth0</name>
      <type>ianaift:ethernetCsmacd</type>
    </interface>
    <interface>
      <name>eth0.3</name>
      <type>ianaift:l2vlan</type>
      <if-ext:parent-interface>eth0</if-ext:parent-interface>
      <if-ext:encapsulation>
        <flexible xmlns=
        "urn:ietf:params:xml:ns:yang:ietf-if-flexible-encapsulation">
          <match>
            <dot1q-vlan-tagged>
              <outer-tag>
                <tag-type>dot1q-types:s-vlan</tag-type>
                <vlan-id>10</vlan-id>
              </outer-tag>
              <second-tag>
                <tag-type>dot1q-types:c-vlan</tag-type>
                <vlan-id>21</vlan-id>
              </second-tag>
            </dot1q-vlan-tagged>
          </match>
          <rewrite>
            <symmetrical>
              <dot1q-tag-rewrite>
                <pop-tags>1</pop-tags>
              </dot1q-tag-rewrite>
            </symmetrical>
          </rewrite>
        </flexible>
      </if-ext:encapsulation>
    </interface>
    <interface>
      <name>eth1</name>
      <type>ianaift:ethernetCsmacd</type>
    </interface>
    <interface>
      <name>eth1.0</name>
      <type>ianaift:l2vlan</type>
      <if-ext:parent-interface>eth0</if-ext:parent-interface>
      <if-ext:encapsulation>
        <flexible xmlns=
        "urn:ietf:params:xml:ns:yang:ietf-if-flexible-encapsulation">
          <match>
            <dot1q-vlan-tagged>
              <outer-tag>
                <tag-type>dot1q-types:c-vlan</tag-type>
                <vlan-id>50</vlan-id>
              </outer-tag>
            </dot1q-vlan-tagged>
          </match>
          <rewrite>
            <symmetrical>
              <dot1q-tag-rewrite>
                <pop-tags>1</pop-tags>
              </dot1q-tag-rewrite>
            </symmetrical>
          </rewrite>
        </flexible>
      </if-ext:encapsulation>
    </interface>
  </interfaces>
  <network-instances
      xmlns="urn:ietf:params:xml:ns:yang:ietf-network-instance">
    <network-instance
     xmlns:l2vpn="urn:ietf:params:xml:ns:yang:ietf-l2vpn">   
      <name>p2p-l2-1</name>
      <description>Point to point L2 service</description>
      <l2vpn:type>l2vpn:vpws-instance-type</l2vpn:type>
      <l2vpn:signaling-type>
        l2vpn:ldp-signaling
      </l2vpn:signaling-type>
      <endpoint xmlns="urn:ietf:params:xml:ns:yang:ietf-l2vpn">
        <name>local</name>
        <ac>
          <name>eth0.3</name>
        </ac>
      </endpoint>
      <endpoint xmlns="urn:ietf:params:xml:ns:yang:ietf-l2vpn">
        <name>remote</name>
        <pw>
          <name>pw1</name>
        </pw>
      </endpoint>
      <vsi-root>
      <!-- Does not Validate -->
      </vsi-root>
    </network-instance>
  </network-instances>
  <pseudowires
      xmlns="urn:ietf:params:xml:ns:yang:ietf-pseudowires">
    <pseudowire>
      <name>pw1</name>
        <peer-ip>2001:db8::50></peer-ip>
        <pw-id>100</pw-id>
    </pseudowire>
  </pseudowires>
</config>
